Metadata-Version: 2.1
Name: Kern-Rowduction
Version: 0.0.4
Summary: Kern Rowduction - A package to reduce the number of rows / undersample the     (imbalanced) datasets by graph kernelisation methods.
Home-page: https://github.com/Kern-Rowduction/Kern-Rowduction
Author: Hichem Boughattas & Hamza Bouanani
Author-email: kern.rowduction@gmail.com
License: UNKNOWN
Download-URL: https://github.com/Kern-Rowduction/Kern-Rowduction/archive/refs/tags/v_0.0.4.tar.gz
Keywords: python,graph,kernel,rowduction,imbalance,data,science,dataset
Platform: UNKNOWN
Classifier: Development Status :: 3 - Alpha
Classifier: Intended Audience :: Developers
Classifier: Intended Audience :: End Users/Desktop
Classifier: Intended Audience :: Science/Research
Classifier: Programming Language :: Python :: 2
Classifier: Programming Language :: Python :: 3
Classifier: Operating System :: MacOS :: MacOS X
Classifier: Operating System :: Microsoft :: Windows
Classifier: Operating System :: POSIX :: Linux
Classifier: Topic :: Scientific/Engineering :: Mathematics
